LICENSE
MANIFEST.in
README.md
setup.py
spyder_screencast/__init__.py
spyder_screencast/api.py
spyder_screencast/container.py
spyder_screencast/plugin.py
spyder_screencast/widgets.py
spyder_screencast.egg-info/PKG-INFO
spyder_screencast.egg-info/SOURCES.txt
spyder_screencast.egg-info/dependency_links.txt
spyder_screencast.egg-info/entry_points.txt
spyder_screencast.egg-info/requires.txt
spyder_screencast.egg-info/top_level.txt